{
  "name": "drawing_images/3ndmjoe8yhfhn2/ARCH_page_1_UHD.jpg",
  "bucket": "ardennes-85ab2.appspot.com",
  "metageneration": 1,
  "generation": 1730465079586,
  "contentType": "image/jpeg",
  "storageClass": "STANDARD",
  "contentDisposition": "inline",
  "downloadTokens": [
    "6d8b323b-6c66-4c5d-9858-4d6c36e8319d"
  ],
  "etag": "aY8vXTbTyb1+8/V+26qSAcqLCYM",
  "customMetadata": {},
  "timeCreated": "2024-11-01T12:44:39.586Z",
  "updated": "2024-11-01T12:44:39.586Z",
  "size": 6884209,
  "md5Hash": "j5F8quioHolM4o8tY/H7Mg==",
  "crc32c": "166626381"
}